myword/__init__.py
myword/tokenizer.py
myword-0.1.1.dist-info/licenses/LICENSE
myword-0.1.1.dist-info/METADATA
myword-0.1.1.dist-info/WHEEL
myword-0.1.1.dist-info/top_level.txt
myword-0.1.1.dist-info/RECORD
