Metadata-Version: 2.4
Name: myword
Version: 0.1.1
Summary: Myanmar (Burmese) Syllable, Word, and Phrase
Home-page: https://github.com/ye-kyaw-thu/myWord
Author: Ye Kyaw Thu
Author-email: yekyaw.thu@nectec.or.th
License: MIT
Classifier: Programming Language :: Python :: 3
Classifier: License :: OSI Approved :: MIT License
Classifier: Operating System :: OS Independent
Requires-Python: >=3.7
License-File: LICENSE
Requires-Dist: cached_path
Dynamic: author
Dynamic: author-email
Dynamic: classifier
Dynamic: description
Dynamic: description-content-type
Dynamic: home-page
Dynamic: license
Dynamic: license-file
Dynamic: requires-dist
Dynamic: requires-python
Dynamic: summary
